AUTHORS
LICENSE
MANIFEST.in
README.rst
setup.py
fabric_provision.egg-info/PKG-INFO
fabric_provision.egg-info/SOURCES.txt
fabric_provision.egg-info/dependency_links.txt
fabric_provision.egg-info/requires.txt
fabric_provision.egg-info/top_level.txt
provision/__init__.py