Metadata-Version: 1.0
Name: fabric-provision
Version: 0.0.4
Summary: Server provisioning with Chef
Home-page: http://github.com/caffeinehit/fabric-provision
Author: Alen Mujezinovic
Author-email: alen@caffeinehit.com
License: UNKNOWN
Keywords: server provisioning fabric chef
Platform: UNKNOWN
